                {
                  "showapi_res_error": "",
                  "showapi_res_id": "3a050327f6bb47d099725ee0bfc44128",
                  "showapi_res_code": 0,
                  "showapi_res_body": {"ret_code":0,"list":[{"date":"2014-10-31","open_price":"9.57","close_price":"9.36","max_price":"9.63","min_price":"9.22","trade_num":"53894","trade_money":"50521616","diff_money":"-0.25","diff_rate":"-2.6","swing":"4.27","turnover":"1.96","market":"sz","code":"002607"},{"date":"2014-10-30","open_price":"9.52","close_price":"9.61","max_price":"9.63","min_price":"9.42","trade_num":"69799","trade_money":"66629654","diff_money":"-0.05","diff_rate":"-0.52","swing":"2.17","turnover":"2.54","market":"sz","code":"002607"},{"date":"2014-10-29","open_price":"9.36","close_price":"9.66","max_price":"9.77","min_price":"9.2","trade_num":"103289","trade_money":"97713185","diff_money":"0.17","diff_rate":"1.79","swing":"6.01","turnover":"3.76","market":"sz","code":"002607"},{"date":"2014-10-28","open_price":"9.31","close_price":"9.49","max_price":"9.53","min_price":"9.27","trade_num":"33908","trade_money":"31970424","diff_money":"0.22","diff_rate":"2.37","swing":"2.80","turnover":"1.24","market":"sz","code":"002607"},{"date":"2014-10-27","open_price":"9.09","close_price":"9.27","max_price":"9.3","min_price":"9.08","trade_num":"16640","trade_money":"15336336","diff_money":"0.11","diff_rate":"1.2","swing":"2.40","turnover":"0.61","market":"sz","code":"002607"},{"date":"2014-10-24","open_price":"9.21","close_price":"9.16","max_price":"9.35","min_price":"9.13","trade_num":"22247","trade_money":"20535758","diff_money":"-0.06","diff_rate":"-0.65","swing":"2.39","turnover":"0.81","market":"sz","code":"002607"},{"date":"2014-10-23","open_price":"9.15","close_price":"9.22","max_price":"9.45","min_price":"9.1","trade_num":"35410","trade_money":"32736332","diff_money":"-0.03","diff_rate":"-0.32","swing":"3.78","turnover":"1.29","market":"sz","code":"002607"},{"date":"2014-10-22","open_price":"9.56","close_price":"9.25","max_price":"9.6","min_price":"9.25","trade_num":"31008","trade_money":"29232434","diff_money":"-0.35","diff_rate":"-3.65","swing":"3.65","turnover":"1.13","market":"sz","code":"002607"},{"date":"2014-10-21","open_price":"9.49","close_price":"9.6","max_price":"9.64","min_price":"9.41","trade_num":"48777","trade_money":"46470905","diff_money":"0.12","diff_rate":"1.27","swing":"2.43","turnover":"1.78","market":"sz","code":"002607"},{"date":"2014-10-20","open_price":"9.49","close_price":"9.48","max_price":"9.57","min_price":"9.29","trade_num":"38237","trade_money":"36204940","diff_money":"0.08","diff_rate":"0.85","swing":"2.98","turnover":"1.39","market":"sz","code":"002607"},{"date":"2014-10-17","open_price":"9.67","close_price":"9.4","max_price":"9.8","min_price":"9.1","trade_num":"61798","trade_money":"58492708","diff_money":"-0.43","diff_rate":"-4.37","swing":"7.12","turnover":"2.25","market":"sz","code":"002607"},{"date":"2014-10-16","open_price":"10.23","close_price":"9.83","max_price":"10.23","min_price":"9.81","trade_num":"83136","trade_money":"83489724","diff_money":"-0.56","diff_rate":"-5.39","swing":"4.04","turnover":"3.03","market":"sz","code":"002607"},{"date":"2014-10-15","open_price":"10.45","close_price":"10.39","max_price":"10.68","min_price":"10.23","trade_num":"66279","trade_money":"69125547","diff_money":"0.02","diff_rate":"0.19","swing":"4.34","turnover":"2.41","market":"sz","code":"002607"},{"date":"2014-10-14","open_price":"10.27","close_price":"10.37","max_price":"10.48","min_price":"10.18","trade_num":"61547","trade_money":"63675785","diff_money":"-0.03","diff_rate":"-0.29","swing":"2.88","turnover":"2.24","market":"sz","code":"002607"},{"date":"2014-10-13","open_price":"10.5","close_price":"10.4","max_price":"10.51","min_price":"10.1","trade_num":"75798","trade_money":"77946666","diff_money":"-0.19","diff_rate":"-1.79","swing":"3.87","turnover":"2.76","market":"sz","code":"002607"},{"date":"2014-10-10","open_price":"10.54","close_price":"10.59","max_price":"10.6","min_price":"10.35","trade_num":"97580","trade_money":"102414542","diff_money":"-0.05","diff_rate":"-0.47","swing":"2.35","turnover":"3.55","market":"sz","code":"002607"},{"date":"2014-10-09","open_price":"11.05","close_price":"10.64","max_price":"11.09","min_price":"10.5","trade_num":"230351","trade_money":"246276678","diff_money":"-0.32","diff_rate":"-2.92","swing":"5.38","turnover":"8.39","market":"sz","code":"002607"},{"date":"2014-10-08","open_price":"10.0","close_price":"10.96","max_price":"10.96","min_price":"9.96","trade_num":"233461","trade_money":"250209206","diff_money":"1.0","diff_rate":"10.04","swing":"10.04","turnover":"8.5","market":"sz","code":"002607"}]}
                }
                
