                {
                  "showapi_res_error": "",
                  "showapi_res_id": "12a163ee90e84c0cbe3f87b0b64feb31",
                  "showapi_res_code": 0,
                  "showapi_res_body": {"ret_code":0,"list":[{"date":"2013-05-31","open_price":"8.03","close_price":"8.11","max_price":"8.19","min_price":"8.01","trade_num":"19119","trade_money":"15470575","diff_money":"0.09","diff_rate":"1.12","swing":"2.24","turnover":"0.61","market":"sh","code":"600629"},{"date":"2013-05-30","open_price":"7.94","close_price":"8.02","max_price":"8.1","min_price":"7.93","trade_num":"17487","trade_money":"14053944","diff_money":"0.06","diff_rate":"0.75","swing":"2.14","turnover":"0.56","market":"sh","code":"600629"},{"date":"2013-05-29","open_price":"7.94","close_price":"7.96","max_price":"8.03","min_price":"7.92","trade_num":"10334","trade_money":"8238215","diff_money":"-0.02","diff_rate":"-0.25","swing":"1.38","turnover":"0.33","market":"sh","code":"600629"},{"date":"2013-05-28","open_price":"7.94","close_price":"7.98","max_price":"8.16","min_price":"7.88","trade_num":"16559","trade_money":"13204122","diff_money":"0.02","diff_rate":"0.25","swing":"3.52","turnover":"0.53","market":"sh","code":"600629"},{"date":"2013-05-27","open_price":"7.88","close_price":"7.96","max_price":"8.0","min_price":"7.82","trade_num":"10780","trade_money":"8540890","diff_money":"0.08","diff_rate":"1.02","swing":"2.28","turnover":"0.35","market":"sh","code":"600629"},{"date":"2013-05-24","open_price":"7.99","close_price":"7.88","max_price":"7.99","min_price":"7.8","trade_num":"9894","trade_money":"7788429","diff_money":"-0.01","diff_rate":"-0.13","swing":"2.41","turnover":"0.32","market":"sh","code":"600629"},{"date":"2013-05-23","open_price":"7.98","close_price":"7.89","max_price":"8.01","min_price":"7.83","trade_num":"12960","trade_money":"10255674","diff_money":"-0.12","diff_rate":"-1.5","swing":"2.25","turnover":"0.42","market":"sh","code":"600629"},{"date":"2013-05-22","open_price":"7.94","close_price":"8.01","max_price":"8.31","min_price":"7.94","trade_num":"27169","trade_money":"22019139","diff_money":"0.12","diff_rate":"1.52","swing":"4.69","turnover":"0.87","market":"sh","code":"600629"},{"date":"2013-05-21","open_price":"7.96","close_price":"7.89","max_price":"7.96","min_price":"7.76","trade_num":"11112","trade_money":"8718793","diff_money":"0.01","diff_rate":"0.13","swing":"2.54","turnover":"0.36","market":"sh","code":"600629"},{"date":"2013-05-20","open_price":"7.85","close_price":"7.88","max_price":"7.93","min_price":"7.7","trade_num":"14148","trade_money":"11079932","diff_money":"0.14","diff_rate":"1.81","swing":"2.97","turnover":"0.45","market":"sh","code":"600629"},{"date":"2013-05-17","open_price":"7.64","close_price":"7.74","max_price":"7.79","min_price":"7.64","trade_num":"12983","trade_money":"10042591","diff_money":"0.11","diff_rate":"1.44","swing":"1.97","turnover":"0.42","market":"sh","code":"600629"},{"date":"2013-05-16","open_price":"7.58","close_price":"7.63","max_price":"7.67","min_price":"7.55","trade_num":"11568","trade_money":"8830511","diff_money":"0.03","diff_rate":"0.39","swing":"1.58","turnover":"0.37","market":"sh","code":"600629"},{"date":"2013-05-15","open_price":"7.56","close_price":"7.6","max_price":"7.63","min_price":"7.47","trade_num":"11510","trade_money":"8693064","diff_money":"0.04","diff_rate":"0.53","swing":"2.12","turnover":"0.37","market":"sh","code":"600629"},{"date":"2013-05-14","open_price":"7.52","close_price":"7.56","max_price":"7.66","min_price":"7.48","trade_num":"10570","trade_money":"7982784","diff_money":"0.0","diff_rate":"0.0","swing":"2.38","turnover":"0.34","market":"sh","code":"600629"},{"date":"2013-05-13","open_price":"7.45","close_price":"7.56","max_price":"7.75","min_price":"7.44","trade_num":"12363","trade_money":"9372471","diff_money":"0.06","diff_rate":"0.8","swing":"4.13","turnover":"0.4","market":"sh","code":"600629"},{"date":"2013-05-10","open_price":"7.37","close_price":"7.5","max_price":"7.54","min_price":"7.33","trade_num":"7601","trade_money":"5682277","diff_money":"0.12","diff_rate":"1.63","swing":"2.85","turnover":"0.24","market":"sh","code":"600629"},{"date":"2013-05-09","open_price":"7.52","close_price":"7.38","max_price":"7.57","min_price":"7.32","trade_num":"10657","trade_money":"7919012","diff_money":"-0.17","diff_rate":"-2.25","swing":"3.31","turnover":"0.34","market":"sh","code":"600629"},{"date":"2013-05-08","open_price":"7.52","close_price":"7.55","max_price":"7.59","min_price":"7.48","trade_num":"7645","trade_money":"5757623","diff_money":"0.01","diff_rate":"0.13","swing":"1.46","turnover":"0.25","market":"sh","code":"600629"},{"date":"2013-05-07","open_price":"7.47","close_price":"7.54","max_price":"7.63","min_price":"7.41","trade_num":"6981","trade_money":"5237613","diff_money":"0.07","diff_rate":"0.94","swing":"2.95","turnover":"0.22","market":"sh","code":"600629"},{"date":"2013-05-06","open_price":"7.46","close_price":"7.47","max_price":"7.5","min_price":"7.4","trade_num":"10446","trade_money":"7782361","diff_money":"0.02","diff_rate":"0.27","swing":"1.34","turnover":"0.34","market":"sh","code":"600629"},{"date":"2013-05-03","open_price":"7.26","close_price":"7.45","max_price":"7.46","min_price":"7.2","trade_num":"10998","trade_money":"8080184","diff_money":"0.23","diff_rate":"3.19","swing":"3.60","turnover":"0.35","market":"sh","code":"600629"},{"date":"2013-05-02","open_price":"7.37","close_price":"7.22","max_price":"7.37","min_price":"7.18","trade_num":"14758","trade_money":"10709748","diff_money":"-0.22","diff_rate":"-2.96","swing":"2.55","turnover":"0.47","market":"sh","code":"600629"}]}
                }
                
