                {
                  "showapi_res_error": "",
                  "showapi_res_id": "a0c9d358003c45bf9506216122438f35",
                  "showapi_res_code": 0,
                  "showapi_res_body": {"ret_code":0,"list":[{"date":"2011-05-31","open_price":"12.01","close_price":"13.29","max_price":"13.29","min_price":"11.76","trade_num":"581010","trade_money":"741040000","diff_money":"1.21","diff_rate":"10.02","swing":"12.67","turnover":"11.26","market":"sh","code":"600572"},{"date":"2011-05-30","open_price":"12.00","close_price":"12.08","max_price":"12.39","min_price":"11.42","trade_num":"274604","trade_money":"328520000","diff_money":"-0.22","diff_rate":"-1.79","swing":"7.89","turnover":"5.32","market":"sh","code":"600572"},{"date":"2011-05-27","open_price":"12.79","close_price":"12.30","max_price":"13.02","min_price":"12.14","trade_num":"459927","trade_money":"568100000","diff_money":"-1.19","diff_rate":"-8.82","swing":"6.52","turnover":"8.91","market":"sh","code":"600572"},{"date":"2011-05-25","open_price":"12.60","close_price":"13.49","max_price":"13.97","min_price":"12.55","trade_num":"753925","trade_money":"1014630000","diff_money":"0.70","diff_rate":"5.47","swing":"11.10","turnover":"14.61","market":"sh","code":"600572"},{"date":"2011-05-24","open_price":"12.99","close_price":"12.79","max_price":"13.23","min_price":"12.43","trade_num":"496926","trade_money":"634940000","diff_money":"-0.31","diff_rate":"-2.37","swing":"6.11","turnover":"9.63","market":"sh","code":"600572"},{"date":"2011-05-23","open_price":"14.01","close_price":"13.10","max_price":"14.09","min_price":"12.83","trade_num":"662932","trade_money":"887500000","diff_money":"-1.05","diff_rate":"-7.42","swing":"8.90","turnover":"12.84","market":"sh","code":"600572"},{"date":"2011-05-19","open_price":"13.13","close_price":"14.15","max_price":"14.48","min_price":"12.91","trade_num":"1066351","trade_money":"1454840000","diff_money":"0.97","diff_rate":"7.36","swing":"11.91","turnover":"20.66","market":"sh","code":"600572"},{"date":"2011-05-18","open_price":"12.80","close_price":"13.18","max_price":"13.76","min_price":"12.71","trade_num":"1032920","trade_money":"1370170000","diff_money":"0.58","diff_rate":"4.60","swing":"8.33","turnover":"20.01","market":"sh","code":"600572"},{"date":"2011-05-17","open_price":"11.35","close_price":"12.60","max_price":"12.60","min_price":"11.29","trade_num":"518899","trade_money":"637620000","diff_money":"1.15","diff_rate":"10.04","swing":"11.44","turnover":"10.05","market":"sh","code":"600572"},{"date":"2011-05-16","open_price":"11.50","close_price":"11.45","max_price":"11.64","min_price":"11.25","trade_num":"157821","trade_money":"180180000","diff_money":"-0.11","diff_rate":"-0.95","swing":"3.37","turnover":"3.06","market":"sh","code":"600572"},{"date":"2011-05-13","open_price":"11.80","close_price":"11.56","max_price":"11.97","min_price":"11.15","trade_num":"265067","trade_money":"305510000","diff_money":"-0.31","diff_rate":"-2.61","swing":"6.91","turnover":"5.14","market":"sh","code":"600572"},{"date":"2011-05-12","open_price":"11.79","close_price":"11.87","max_price":"12.38","min_price":"11.79","trade_num":"272186","trade_money":"328650000","diff_money":"-0.22","diff_rate":"-1.82","swing":"4.88","turnover":"5.27","market":"sh","code":"600572"},{"date":"2011-05-11","open_price":"12.39","close_price":"12.09","max_price":"12.39","min_price":"11.85","trade_num":"333805","trade_money":"403060000","diff_money":"-0.34","diff_rate":"-2.74","swing":"4.34","turnover":"6.47","market":"sh","code":"600572"},{"date":"2011-05-10","open_price":"12.43","close_price":"12.43","max_price":"12.67","min_price":"12.25","trade_num":"370647","trade_money":"460290000","diff_money":"-0.07","diff_rate":"-0.56","swing":"3.36","turnover":"7.18","market":"sh","code":"600572"},{"date":"2011-05-09","open_price":"12.60","close_price":"12.50","max_price":"12.74","min_price":"12.23","trade_num":"395893","trade_money":"494360000","diff_money":"-0.14","diff_rate":"-1.11","swing":"4.03","turnover":"7.67","market":"sh","code":"600572"},{"date":"2011-05-06","open_price":"12.00","close_price":"12.64","max_price":"12.79","min_price":"11.81","trade_num":"604132","trade_money":"748770000","diff_money":"0.37","diff_rate":"3.02","swing":"7.99","turnover":"11.71","market":"sh","code":"600572"},{"date":"2011-05-05","open_price":"12.34","close_price":"12.27","max_price":"12.82","min_price":"11.89","trade_num":"862636","trade_money":"1067340000","diff_money":"0.41","diff_rate":"3.46","swing":"7.84","turnover":"16.71","market":"sh","code":"600572"},{"date":"2011-05-04","open_price":"10.90","close_price":"11.86","max_price":"11.86","min_price":"10.80","trade_num":"382554","trade_money":"440430000","diff_money":"1.08","diff_rate":"10.02","swing":"9.83","turnover":"7.41","market":"sh","code":"600572"}]}
                }
                
