{
                  "showapi_res_error": "",
                  "showapi_res_id": "c5b8045d1bf14574959284db712ba1f7",
                  "showapi_res_code": 0,
                  "showapi_res_body": {"ret_code":0,"list":[{"date":"2018-11-30","open_price":"14.69","close_price":"15.65","max_price":"16.05","min_price":"14.69","trade_num":"16286","trade_money":"25262318","diff_money":"0.87","diff_rate":"5.89","swing":"9.20","turnover":"1.02","market":"sz","code":"300414"},{"date":"2018-11-29","open_price":"15.39","close_price":"14.78","max_price":"15.58","min_price":"14.72","trade_num":"10835","trade_money":"16540155","diff_money":"-0.37","diff_rate":"-2.44","swing":"5.68","turnover":"0.69","market":"sz","code":"300414"},{"date":"2018-11-28","open_price":"15.13","close_price":"15.15","max_price":"15.57","min_price":"15.05","trade_num":"8752","trade_money":"13378942","diff_money":"-0.24","diff_rate":"-1.56","swing":"3.38","turnover":"0.55","market":"sz","code":"300414"},{"date":"2018-11-27","open_price":"15.17","close_price":"15.39","max_price":"15.63","min_price":"15.17","trade_num":"5179","trade_money":"7993434","diff_money":"0.25","diff_rate":"1.65","swing":"3.04","turnover":"0.33","market":"sz","code":"300414"},{"date":"2018-11-26","open_price":"14.9","close_price":"15.14","max_price":"15.47","min_price":"14.9","trade_num":"6492","trade_money":"9886833","diff_money":"0.14","diff_rate":"0.93","swing":"3.80","turnover":"0.41","market":"sz","code":"300414"},{"date":"2018-11-23","open_price":"15.72","close_price":"15.0","max_price":"16.0","min_price":"14.98","trade_num":"7996","trade_money":"12271336","diff_money":"-0.89","diff_rate":"-5.6","swing":"6.42","turnover":"0.49","market":"sz","code":"300414"},{"date":"2018-11-22","open_price":"15.91","close_price":"15.89","max_price":"16.08","min_price":"15.46","trade_num":"8960","trade_money":"14087970","diff_money":"0.17","diff_rate":"1.08","swing":"3.94","turnover":"0.56","market":"sz","code":"300414"},{"date":"2018-11-21","open_price":"15.3","close_price":"15.72","max_price":"15.94","min_price":"15.16","trade_num":"9187","trade_money":"14306040","diff_money":"0.04","diff_rate":"0.26","swing":"4.97","turnover":"0.58","market":"sz","code":"300414"},{"date":"2018-11-20","open_price":"16.01","close_price":"15.68","max_price":"16.08","min_price":"15.36","trade_num":"22014","trade_money":"34553864","diff_money":"-0.52","diff_rate":"-3.21","swing":"4.44","turnover":"1.39","market":"sz","code":"300414"},{"date":"2018-11-19","open_price":"14.92","close_price":"16.2","max_price":"16.4","min_price":"14.92","trade_num":"30935","trade_money":"49231465","diff_money":"1.29","diff_rate":"8.65","swing":"9.93","turnover":"1.95","market":"sz","code":"300414"},{"date":"2018-11-16","open_price":"14.71","close_price":"14.91","max_price":"15.22","min_price":"14.41","trade_num":"17014","trade_money":"25139835","diff_money":"0.36","diff_rate":"2.47","swing":"5.57","turnover":"1.08","market":"sz","code":"300414"},{"date":"2018-11-15","open_price":"13.52","close_price":"14.55","max_price":"14.55","min_price":"13.52","trade_num":"13249","trade_money":"18793029","diff_money":"0.84","diff_rate":"6.13","swing":"7.51","turnover":"0.82","market":"sz","code":"300414"},{"date":"2018-11-14","open_price":"13.73","close_price":"13.71","max_price":"13.96","min_price":"13.54","trade_num":"7339","trade_money":"10116441","diff_money":"-0.04","diff_rate":"-0.29","swing":"3.05","turnover":"0.46","market":"sz","code":"300414"},{"date":"2018-11-13","open_price":"13.07","close_price":"13.75","max_price":"13.81","min_price":"13.06","trade_num":"7445","trade_money":"10124659","diff_money":"0.26","diff_rate":"1.93","swing":"5.56","turnover":"0.46","market":"sz","code":"300414"},{"date":"2018-11-12","open_price":"12.99","close_price":"13.49","max_price":"13.53","min_price":"12.87","trade_num":"6862","trade_money":"9154768","diff_money":"0.5","diff_rate":"3.85","swing":"5.08","turnover":"0.43","market":"sz","code":"300414"},{"date":"2018-11-09","open_price":"13.41","close_price":"12.99","max_price":"13.41","min_price":"12.91","trade_num":"3967","trade_money":"5207237","diff_money":"-0.03","diff_rate":"-0.23","swing":"3.84","turnover":"0.25","market":"sz","code":"300414"},{"date":"2018-11-08","open_price":"13.03","close_price":"13.02","max_price":"13.32","min_price":"12.92","trade_num":"4393","trade_money":"5754456","diff_money":"-0.01","diff_rate":"-0.08","swing":"3.07","turnover":"0.27","market":"sz","code":"300414"},{"date":"2018-11-07","open_price":"13.02","close_price":"13.03","max_price":"13.37","min_price":"12.93","trade_num":"5410","trade_money":"7099078","diff_money":"-0.05","diff_rate":"-0.38","swing":"3.36","turnover":"0.34","market":"sz","code":"300414"},{"date":"2018-11-06","open_price":"13.44","close_price":"13.08","max_price":"13.44","min_price":"12.95","trade_num":"5910","trade_money":"7731884","diff_money":"-0.31","diff_rate":"-2.32","swing":"3.66","turnover":"0.37","market":"sz","code":"300414"},{"date":"2018-11-05","open_price":"12.96","close_price":"13.39","max_price":"13.85","min_price":"12.96","trade_num":"13537","trade_money":"18153289","diff_money":"0.47","diff_rate":"3.64","swing":"6.89","turnover":"0.85","market":"sz","code":"300414"},{"date":"2018-11-02","open_price":"12.8","close_price":"12.92","max_price":"13.08","min_price":"12.69","trade_num":"9868","trade_money":"12718922","diff_money":"0.46","diff_rate":"3.69","swing":"3.13","turnover":"0.62","market":"sz","code":"300414"},{"date":"2018-11-01","open_price":"12.55","close_price":"12.46","max_price":"12.8","min_price":"12.43","trade_num":"7213","trade_money":"9120304","diff_money":"0.01","diff_rate":"0.08","swing":"2.97","turnover":"0.45","market":"sz","code":"300414"}]}
                }

