                {
                  "showapi_res_error": "",
                  "showapi_res_id": "c1c41545dc6548f8bb3e75a5faf13621",
                  "showapi_res_code": 0,
                  "showapi_res_body": {"ret_code":0,"list":[{"date":"2013-03-29","open_price":"12.19","close_price":"12.63","max_price":"12.74","min_price":"12.12","trade_num":"1023329","trade_money":"1272875637","diff_money":"0.5","diff_rate":"4.12","swing":"5.11","turnover":"0.58","market":"sh","code":"600036"},{"date":"2013-03-28","open_price":"12.4","close_price":"12.13","max_price":"12.4","min_price":"11.7","trade_num":"1266172","trade_money":"1535552202","diff_money":"-0.64","diff_rate":"-5.01","swing":"5.48","turnover":"0.72","market":"sh","code":"600036"},{"date":"2013-03-27","open_price":"12.66","close_price":"12.77","max_price":"12.92","min_price":"12.66","trade_num":"457293","trade_money":"584254908","diff_money":"0.08","diff_rate":"0.63","swing":"2.05","turnover":"0.26","market":"sh","code":"600036"},{"date":"2013-03-26","open_price":"12.9","close_price":"12.69","max_price":"12.95","min_price":"12.58","trade_num":"619026","trade_money":"786734118","diff_money":"-0.29","diff_rate":"-2.23","swing":"2.85","turnover":"0.35","market":"sh","code":"600036"},{"date":"2013-03-25","open_price":"13.2","close_price":"12.98","max_price":"13.28","min_price":"12.94","trade_num":"559001","trade_money":"730187054","diff_money":"-0.15","diff_rate":"-1.14","swing":"2.59","turnover":"0.32","market":"sh","code":"600036"},{"date":"2013-03-22","open_price":"13.19","close_price":"13.13","max_price":"13.25","min_price":"13.05","trade_num":"441087","trade_money":"579895284","diff_money":"0.0","diff_rate":"0.0","swing":"1.52","turnover":"0.25","market":"sh","code":"600036"},{"date":"2013-03-21","open_price":"13.14","close_price":"13.13","max_price":"13.22","min_price":"13.06","trade_num":"645564","trade_money":"848701343","diff_money":"-0.01","diff_rate":"-0.08","swing":"1.22","turnover":"0.37","market":"sh","code":"600036"},{"date":"2013-03-20","open_price":"12.63","close_price":"13.14","max_price":"13.17","min_price":"12.61","trade_num":"1343233","trade_money":"1745000331","diff_money":"0.54","diff_rate":"4.29","swing":"4.44","turnover":"0.76","market":"sh","code":"600036"},{"date":"2013-03-19","open_price":"12.45","close_price":"12.6","max_price":"12.67","min_price":"12.45","trade_num":"547396","trade_money":"686425566","diff_money":"0.12","diff_rate":"0.96","swing":"1.76","turnover":"0.31","market":"sh","code":"600036"},{"date":"2013-03-18","open_price":"12.48","close_price":"12.48","max_price":"12.7","min_price":"12.4","trade_num":"659537","trade_money":"827700016","diff_money":"-0.09","diff_rate":"-0.72","swing":"2.39","turnover":"0.37","market":"sh","code":"600036"},{"date":"2013-03-15","open_price":"12.68","close_price":"12.57","max_price":"13.19","min_price":"12.44","trade_num":"1361573","trade_money":"1735409883","diff_money":"-0.1","diff_rate":"-0.79","swing":"5.92","turnover":"0.77","market":"sh","code":"600036"},{"date":"2013-03-14","open_price":"12.64","close_price":"12.67","max_price":"12.88","min_price":"12.55","trade_num":"475698","trade_money":"603557988","diff_money":"0.0","diff_rate":"0.0","swing":"2.60","turnover":"0.27","market":"sh","code":"600036"},{"date":"2013-03-13","open_price":"12.9","close_price":"12.67","max_price":"13.03","min_price":"12.6","trade_num":"659828","trade_money":"843335588","diff_money":"-0.23","diff_rate":"-1.78","swing":"3.33","turnover":"0.37","market":"sh","code":"600036"},{"date":"2013-03-12","open_price":"13.12","close_price":"12.9","max_price":"13.3","min_price":"12.75","trade_num":"696099","trade_money":"906390226","diff_money":"-0.22","diff_rate":"-1.68","swing":"4.19","turnover":"0.39","market":"sh","code":"600036"},{"date":"2013-03-11","open_price":"13.21","close_price":"13.12","max_price":"13.23","min_price":"12.96","trade_num":"483437","trade_money":"634664600","diff_money":"-0.21","diff_rate":"-1.58","swing":"2.03","turnover":"0.27","market":"sh","code":"600036"},{"date":"2013-03-08","open_price":"13.15","close_price":"13.33","max_price":"13.48","min_price":"12.93","trade_num":"929944","trade_money":"1230262753","diff_money":"0.22","diff_rate":"1.68","swing":"4.20","turnover":"0.53","market":"sh","code":"600036"},{"date":"2013-03-07","open_price":"13.37","close_price":"13.11","max_price":"13.37","min_price":"12.99","trade_num":"888190","trade_money":"1171202325","diff_money":"-0.34","diff_rate":"-2.53","swing":"2.83","turnover":"0.5","market":"sh","code":"600036"},{"date":"2013-03-06","open_price":"13.37","close_price":"13.45","max_price":"13.6","min_price":"13.14","trade_num":"1529534","trade_money":"2050199178","diff_money":"0.09","diff_rate":"0.67","swing":"3.44","turnover":"0.87","market":"sh","code":"600036"},{"date":"2013-03-05","open_price":"12.33","close_price":"13.36","max_price":"13.47","min_price":"12.33","trade_num":"2174891","trade_money":"2799557374","diff_money":"1.09","diff_rate":"8.88","swing":"9.29","turnover":"1.23","market":"sh","code":"600036"},{"date":"2013-03-04","open_price":"12.85","close_price":"12.27","max_price":"13.0","min_price":"12.17","trade_num":"1747873","trade_money":"2202216042","diff_money":"-0.8","diff_rate":"-6.12","swing":"6.35","turnover":"0.99","market":"sh","code":"600036"},{"date":"2013-03-01","open_price":"13.3","close_price":"13.07","max_price":"13.37","min_price":"12.81","trade_num":"1279527","trade_money":"1676102123","diff_money":"-0.23","diff_rate":"-1.73","swing":"4.21","turnover":"0.72","market":"sh","code":"600036"}]}
                }
                
