                {
                  "showapi_res_error": "",
                  "showapi_res_id": "3f3acbfda47041cd8b53eab82b3e2e38",
                  "showapi_res_code": 0,
                  "showapi_res_body": {"ret_code":0,"list":[{"date":"2017-08-31","open_price":"20.2","close_price":"19.88","max_price":"20.2","min_price":"19.8","trade_num":"130615","trade_money":"260149589","diff_money":"-0.4","diff_rate":"-1.97","swing":"1.97","turnover":"7.43","market":"sz","code":"000011"},{"date":"2017-08-30","open_price":"19.58","close_price":"20.28","max_price":"20.78","min_price":"19.52","trade_num":"213728","trade_money":"431661210","diff_money":"0.83","diff_rate":"4.27","swing":"6.48","turnover":"12.15","market":"sz","code":"000011"},{"date":"2017-08-29","open_price":"19.9","close_price":"19.45","max_price":"20.33","min_price":"19.33","trade_num":"161732","trade_money":"318184797","diff_money":"0.33","diff_rate":"1.73","swing":"5.23","turnover":"9.2","market":"sz","code":"000011"},{"date":"2017-08-28","open_price":"18.76","close_price":"19.12","max_price":"19.2","min_price":"18.76","trade_num":"80793","trade_money":"153605465","diff_money":"0.29","diff_rate":"1.54","swing":"2.34","turnover":"4.59","market":"sz","code":"000011"},{"date":"2017-08-25","open_price":"18.64","close_price":"18.83","max_price":"18.93","min_price":"18.53","trade_num":"44155","trade_money":"82882008","diff_money":"0.19","diff_rate":"1.02","swing":"2.15","turnover":"2.51","market":"sz","code":"000011"},{"date":"2017-08-24","open_price":"18.79","close_price":"18.64","max_price":"18.99","min_price":"18.5","trade_num":"47661","trade_money":"89059002","diff_money":"-0.18","diff_rate":"-0.96","swing":"2.60","turnover":"2.71","market":"sz","code":"000011"},{"date":"2017-08-23","open_price":"19.09","close_price":"18.82","max_price":"19.09","min_price":"18.8","trade_num":"62586","trade_money":"118167719","diff_money":"-0.33","diff_rate":"-1.72","swing":"1.51","turnover":"3.56","market":"sz","code":"000011"},{"date":"2017-08-22","open_price":"19.1","close_price":"19.15","max_price":"19.44","min_price":"19.0","trade_num":"101835","trade_money":"195704352","diff_money":"0.2","diff_rate":"1.06","swing":"2.32","turnover":"5.79","market":"sz","code":"000011"},{"date":"2017-08-21","open_price":"18.95","close_price":"18.95","max_price":"19.16","min_price":"18.82","trade_num":"71506","trade_money":"135406025","diff_money":"-0.08","diff_rate":"-0.42","swing":"1.79","turnover":"4.07","market":"sz","code":"000011"},{"date":"2017-08-18","open_price":"18.57","close_price":"19.03","max_price":"19.1","min_price":"18.43","trade_num":"117897","trade_money":"222680688","diff_money":"0.4","diff_rate":"2.15","swing":"3.60","turnover":"6.7","market":"sz","code":"000011"},{"date":"2017-08-17","open_price":"18.34","close_price":"18.63","max_price":"18.76","min_price":"18.34","trade_num":"63324","trade_money":"117758138","diff_money":"0.23","diff_rate":"1.25","swing":"2.28","turnover":"3.6","market":"sz","code":"000011"},{"date":"2017-08-16","open_price":"18.51","close_price":"18.4","max_price":"18.51","min_price":"18.3","trade_num":"32836","trade_money":"60403733","diff_money":"-0.11","diff_rate":"-0.59","swing":"1.13","turnover":"1.87","market":"sz","code":"000011"},{"date":"2017-08-15","open_price":"18.47","close_price":"18.51","max_price":"18.56","min_price":"18.32","trade_num":"40861","trade_money":"75374620","diff_money":"0.1","diff_rate":"0.54","swing":"1.30","turnover":"2.32","market":"sz","code":"000011"},{"date":"2017-08-14","open_price":"18.2","close_price":"18.41","max_price":"18.47","min_price":"18.16","trade_num":"36181","trade_money":"66451850","diff_money":"0.2","diff_rate":"1.1","swing":"1.70","turnover":"2.06","market":"sz","code":"000011"},{"date":"2017-08-11","open_price":"18.8","close_price":"18.21","max_price":"18.81","min_price":"18.18","trade_num":"79407","trade_money":"146830754","diff_money":"-0.78","diff_rate":"-4.11","swing":"3.32","turnover":"4.52","market":"sz","code":"000011"},{"date":"2017-08-10","open_price":"18.65","close_price":"18.99","max_price":"19.12","min_price":"18.52","trade_num":"88447","trade_money":"166546589","diff_money":"0.34","diff_rate":"1.82","swing":"3.22","turnover":"5.03","market":"sz","code":"000011"},{"date":"2017-08-09","open_price":"18.61","close_price":"18.65","max_price":"18.86","min_price":"18.56","trade_num":"41898","trade_money":"78347595","diff_money":"-0.08","diff_rate":"-0.43","swing":"1.60","turnover":"2.38","market":"sz","code":"000011"},{"date":"2017-08-08","open_price":"18.46","close_price":"18.73","max_price":"19.0","min_price":"18.32","trade_num":"63243","trade_money":"118195016","diff_money":"0.12","diff_rate":"0.64","swing":"3.65","turnover":"3.6","market":"sz","code":"000011"},{"date":"2017-08-07","open_price":"18.72","close_price":"18.61","max_price":"18.8","min_price":"18.5","trade_num":"34428","trade_money":"64281862","diff_money":"0.11","diff_rate":"0.59","swing":"1.62","turnover":"1.96","market":"sz","code":"000011"},{"date":"2017-08-04","open_price":"18.7","close_price":"18.5","max_price":"18.83","min_price":"18.45","trade_num":"57366","trade_money":"106691290","diff_money":"-0.19","diff_rate":"-1.02","swing":"2.03","turnover":"3.26","market":"sz","code":"000011"},{"date":"2017-08-03","open_price":"18.78","close_price":"18.69","max_price":"18.79","min_price":"18.6","trade_num":"71803","trade_money":"134223904","diff_money":"-0.27","diff_rate":"-1.42","swing":"1.00","turnover":"4.08","market":"sz","code":"000011"},{"date":"2017-08-02","open_price":"19.36","close_price":"18.96","max_price":"19.6","min_price":"18.93","trade_num":"87829","trade_money":"168909343","diff_money":"-0.4","diff_rate":"-2.07","swing":"3.46","turnover":"4.99","market":"sz","code":"000011"},{"date":"2017-08-01","open_price":"19.18","close_price":"19.36","max_price":"19.49","min_price":"19.03","trade_num":"102303","trade_money":"197886575","diff_money":"0.27","diff_rate":"1.41","swing":"2.41","turnover":"5.82","market":"sz","code":"000011"}]}
                }
                
