                {
                  "showapi_res_error": "",
                  "showapi_res_id": "8c2b586763204d468e45d175fe540140",
                  "showapi_res_code": 0,
                  "showapi_res_body": {"ret_code":0,"list":[{"date":"2017-07-31","open_price":"8.75","close_price":"8.91","max_price":"8.97","min_price":"8.72","trade_num":"132443","trade_money":"117187289","diff_money":"0.14","diff_rate":"1.6","swing":"2.85","turnover":"1.68","market":"sh","code":"600807"},{"date":"2017-07-28","open_price":"8.82","close_price":"8.77","max_price":"8.91","min_price":"8.75","trade_num":"90589","trade_money":"79660813","diff_money":"-0.08","diff_rate":"-0.9","swing":"1.81","turnover":"1.15","market":"sh","code":"600807"},{"date":"2017-07-27","open_price":"8.74","close_price":"8.85","max_price":"8.89","min_price":"8.71","trade_num":"101682","trade_money":"89495930","diff_money":"0.13","diff_rate":"1.49","swing":"2.06","turnover":"1.29","market":"sh","code":"600807"},{"date":"2017-07-26","open_price":"8.77","close_price":"8.72","max_price":"8.8","min_price":"8.67","trade_num":"80046","trade_money":"69778863","diff_money":"-0.05","diff_rate":"-0.57","swing":"1.48","turnover":"1.02","market":"sh","code":"600807"},{"date":"2017-07-25","open_price":"8.88","close_price":"8.77","max_price":"8.88","min_price":"8.71","trade_num":"79047","trade_money":"69385398","diff_money":"-0.12","diff_rate":"-1.35","swing":"1.91","turnover":"1.0","market":"sh","code":"600807"},{"date":"2017-07-24","open_price":"8.82","close_price":"8.89","max_price":"8.93","min_price":"8.77","trade_num":"77424","trade_money":"68554808","diff_money":"0.07","diff_rate":"0.79","swing":"1.81","turnover":"0.98","market":"sh","code":"600807"},{"date":"2017-07-21","open_price":"8.95","close_price":"8.82","max_price":"8.97","min_price":"8.8","trade_num":"94748","trade_money":"84167028","diff_money":"-0.11","diff_rate":"-1.23","swing":"1.90","turnover":"1.2","market":"sh","code":"600807"},{"date":"2017-07-20","open_price":"8.83","close_price":"8.93","max_price":"9.03","min_price":"8.78","trade_num":"119615","trade_money":"106512349","diff_money":"0.11","diff_rate":"1.25","swing":"2.83","turnover":"1.52","market":"sh","code":"600807"},{"date":"2017-07-19","open_price":"8.62","close_price":"8.82","max_price":"8.88","min_price":"8.59","trade_num":"103749","trade_money":"91210070","diff_money":"0.21","diff_rate":"2.44","swing":"3.37","turnover":"1.32","market":"sh","code":"600807"},{"date":"2017-07-18","open_price":"8.59","close_price":"8.61","max_price":"8.65","min_price":"8.51","trade_num":"81335","trade_money":"69739931","diff_money":"0.1","diff_rate":"1.18","swing":"1.65","turnover":"1.03","market":"sh","code":"600807"},{"date":"2017-07-17","open_price":"9.08","close_price":"8.51","max_price":"9.15","min_price":"8.5","trade_num":"182578","trade_money":"159882667","diff_money":"-0.57","diff_rate":"-6.28","swing":"7.16","turnover":"2.32","market":"sh","code":"600807"},{"date":"2017-07-14","open_price":"9.13","close_price":"9.08","max_price":"9.19","min_price":"9.06","trade_num":"86824","trade_money":"79163525","diff_money":"-0.12","diff_rate":"-1.3","swing":"1.41","turnover":"1.1","market":"sh","code":"600807"},{"date":"2017-07-13","open_price":"9.03","close_price":"9.2","max_price":"9.3","min_price":"8.97","trade_num":"132842","trade_money":"121734393","diff_money":"0.18","diff_rate":"2.0","swing":"3.66","turnover":"1.69","market":"sh","code":"600807"},{"date":"2017-07-12","open_price":"9.0","close_price":"9.02","max_price":"9.05","min_price":"8.89","trade_num":"98733","trade_money":"88656883","diff_money":"0.02","diff_rate":"0.22","swing":"1.78","turnover":"1.25","market":"sh","code":"600807"},{"date":"2017-07-11","open_price":"9.25","close_price":"9.0","max_price":"9.26","min_price":"8.98","trade_num":"130566","trade_money":"118968278","diff_money":"-0.24","diff_rate":"-2.6","swing":"3.03","turnover":"1.66","market":"sh","code":"600807"},{"date":"2017-07-10","open_price":"9.31","close_price":"9.24","max_price":"9.33","min_price":"9.21","trade_num":"108167","trade_money":"100195409","diff_money":"-0.11","diff_rate":"-1.18","swing":"1.28","turnover":"1.37","market":"sh","code":"600807"},{"date":"2017-07-07","open_price":"9.31","close_price":"9.35","max_price":"9.38","min_price":"9.24","trade_num":"136020","trade_money":"126451749","diff_money":"0.04","diff_rate":"0.43","swing":"1.50","turnover":"1.73","market":"sh","code":"600807"},{"date":"2017-07-06","open_price":"9.31","close_price":"9.31","max_price":"9.38","min_price":"9.25","trade_num":"119826","trade_money":"111656434","diff_money":"-0.02","diff_rate":"-0.21","swing":"1.39","turnover":"1.52","market":"sh","code":"600807"},{"date":"2017-07-05","open_price":"9.24","close_price":"9.33","max_price":"9.34","min_price":"9.22","trade_num":"100010","trade_money":"92895472","diff_money":"0.04","diff_rate":"0.43","swing":"1.29","turnover":"1.27","market":"sh","code":"600807"},{"date":"2017-07-04","open_price":"9.38","close_price":"9.29","max_price":"9.45","min_price":"9.26","trade_num":"131345","trade_money":"122468302","diff_money":"-0.12","diff_rate":"-1.28","swing":"2.02","turnover":"1.67","market":"sh","code":"600807"},{"date":"2017-07-03","open_price":"9.33","close_price":"9.41","max_price":"9.47","min_price":"9.31","trade_num":"137337","trade_money":"128953094","diff_money":"-0.02","diff_rate":"-0.21","swing":"1.70","turnover":"1.75","market":"sh","code":"600807"}]}
                }
                
