                {
                  "showapi_res_error": "",
                  "showapi_res_id": "69cc85a7d0444a479eaddd1e9ec21b8e",
                  "showapi_res_code": 0,
                  "showapi_res_body": {"ret_code":0,"list":[{"date":"2015-06-30","open_price":"21.17","close_price":"23.1","max_price":"24.25","min_price":"21.17","trade_num":"124304","trade_money":"275976462","diff_money":"-0.42","diff_rate":"-1.79","swing":"13.10","turnover":"3.77","market":"sh","code":"600764"},{"date":"2015-06-29","open_price":"26.13","close_price":"23.52","max_price":"26.13","min_price":"23.52","trade_num":"70687","trade_money":"168852600","diff_money":"-2.61","diff_rate":"-9.99","swing":"9.99","turnover":"2.14","market":"sh","code":"600764"},{"date":"2015-06-26","open_price":"27.0","close_price":"26.13","max_price":"27.49","min_price":"26.13","trade_num":"58020","trade_money":"153115085","diff_money":"-2.9","diff_rate":"-9.99","swing":"4.68","turnover":"1.76","market":"sh","code":"600764"},{"date":"2015-06-25","open_price":"29.25","close_price":"29.04","max_price":"31.2","min_price":"28.0","trade_num":"87991","trade_money":"262680380","diff_money":"0.04","diff_rate":"0.14","swing":"11.03","turnover":"2.67","market":"sh","code":"600764"},{"date":"2015-06-24","open_price":"29.96","close_price":"29.0","max_price":"30.3","min_price":"27.8","trade_num":"101403","trade_money":"293205403","diff_money":"-0.29","diff_rate":"-0.99","swing":"8.54","turnover":"3.08","market":"sh","code":"600764"},{"date":"2015-06-23","open_price":"31.68","close_price":"29.29","max_price":"32.39","min_price":"28.51","trade_num":"82806","trade_money":"245041263","diff_money":"-2.39","diff_rate":"-7.54","swing":"12.25","turnover":"2.51","market":"sh","code":"600764"},{"date":"2015-06-19","open_price":"33.0","close_price":"31.68","max_price":"34.02","min_price":"31.68","trade_num":"77704","trade_money":"255227249","diff_money":"-3.52","diff_rate":"-10.0","swing":"6.65","turnover":"2.36","market":"sh","code":"600764"},{"date":"2015-06-18","open_price":"34.5","close_price":"35.2","max_price":"38.25","min_price":"34.17","trade_num":"116833","trade_money":"426610723","diff_money":"0.42","diff_rate":"1.21","swing":"11.73","turnover":"3.54","market":"sh","code":"600764"},{"date":"2015-06-17","open_price":"31.08","close_price":"34.78","max_price":"35.1","min_price":"29.8","trade_num":"83958","trade_money":"269846156","diff_money":"2.77","diff_rate":"8.65","swing":"16.56","turnover":"2.55","market":"sh","code":"600764"},{"date":"2015-06-16","open_price":"34.7","close_price":"32.01","max_price":"34.7","min_price":"31.55","trade_num":"91865","trade_money":"306842677","diff_money":"-2.88","diff_rate":"-8.25","swing":"9.03","turnover":"2.79","market":"sh","code":"600764"},{"date":"2015-06-15","open_price":"33.3","close_price":"34.89","max_price":"35.69","min_price":"32.97","trade_num":"92829","trade_money":"320530282","diff_money":"1.66","diff_rate":"5.0","swing":"8.19","turnover":"2.82","market":"sh","code":"600764"},{"date":"2015-06-12","open_price":"32.33","close_price":"33.23","max_price":"35.35","min_price":"31.5","trade_num":"84513","trade_money":"277435039","diff_money":"0.86","diff_rate":"2.66","swing":"11.89","turnover":"2.56","market":"sh","code":"600764"},{"date":"2015-06-11","open_price":"30.95","close_price":"32.37","max_price":"32.4","min_price":"30.56","trade_num":"81469","trade_money":"256390086","diff_money":"1.26","diff_rate":"4.05","swing":"5.91","turnover":"2.47","market":"sh","code":"600764"},{"date":"2015-06-10","open_price":"29.0","close_price":"31.11","max_price":"31.8","min_price":"28.55","trade_num":"89483","trade_money":"273445317","diff_money":"1.55","diff_rate":"5.24","swing":"10.99","turnover":"2.71","market":"sh","code":"600764"},{"date":"2015-06-09","open_price":"30.0","close_price":"29.56","max_price":"30.38","min_price":"28.6","trade_num":"64107","trade_money":"189030571","diff_money":"-0.6","diff_rate":"-1.99","swing":"5.90","turnover":"1.94","market":"sh","code":"600764"},{"date":"2015-06-08","open_price":"29.78","close_price":"30.16","max_price":"31.09","min_price":"29.08","trade_num":"116412","trade_money":"353810837","diff_money":"0.38","diff_rate":"1.28","swing":"6.75","turnover":"3.53","market":"sh","code":"600764"},{"date":"2015-06-05","open_price":"27.85","close_price":"29.78","max_price":"30.22","min_price":"27.82","trade_num":"101544","trade_money":"291395891","diff_money":"2.03","diff_rate":"7.32","swing":"8.65","turnover":"3.08","market":"sh","code":"600764"},{"date":"2015-06-04","open_price":"28.68","close_price":"27.75","max_price":"28.98","min_price":"25.72","trade_num":"63888","trade_money":"174606143","diff_money":"-0.83","diff_rate":"-2.9","swing":"11.41","turnover":"1.94","market":"sh","code":"600764"},{"date":"2015-06-03","open_price":"29.8","close_price":"28.58","max_price":"30.0","min_price":"27.6","trade_num":"66642","trade_money":"191883547","diff_money":"-1.0","diff_rate":"-3.38","swing":"8.11","turnover":"2.02","market":"sh","code":"600764"},{"date":"2015-06-02","open_price":"28.03","close_price":"29.58","max_price":"30.09","min_price":"27.6","trade_num":"78035","trade_money":"225616936","diff_money":"1.65","diff_rate":"5.91","swing":"8.92","turnover":"2.37","market":"sh","code":"600764"},{"date":"2015-06-01","open_price":"26.7","close_price":"27.93","max_price":"27.94","min_price":"26.43","trade_num":"59326","trade_money":"163064094","diff_money":"1.35","diff_rate":"5.08","swing":"5.68","turnover":"1.8","market":"sh","code":"600764"}]}
                }
                
