                {
                  "showapi_res_error": "",
                  "showapi_res_id": "341b8af249ee4d05a5764ae37f96bd9c",
                  "showapi_res_code": 0,
                  "showapi_res_body": {"ret_code":0,"list":[{"date":"2010-03-31","open_price":"42.80","close_price":"44.57","max_price":"45.00","min_price":"42.43","trade_num":"83596","trade_money":"363790000","diff_money":"1.71","diff_rate":"3.99","swing":"6.00","turnover":"27.50","market":"sz","code":"002376"},{"date":"2010-03-30","open_price":"41.65","close_price":"42.86","max_price":"43.44","min_price":"40.80","trade_num":"87637","trade_money":"371010000","diff_money":"1.23","diff_rate":"2.95","swing":"6.34","turnover":"28.83","market":"sz","code":"002376"},{"date":"2010-03-29","open_price":"41.02","close_price":"41.63","max_price":"42.18","min_price":"39.70","trade_num":"94398","trade_money":"385390000","diff_money":"0.64","diff_rate":"1.56","swing":"6.05","turnover":"31.05","market":"sz","code":"002376"},{"date":"2010-03-26","open_price":"40.70","close_price":"40.99","max_price":"41.50","min_price":"40.20","trade_num":"90882","trade_money":"371520000","diff_money":"-1.17","diff_rate":"-2.78","swing":"3.08","turnover":"29.90","market":"sz","code":"002376"},{"date":"2010-03-25","open_price":"41.60","close_price":"42.16","max_price":"43.56","min_price":"41.22","trade_num":"149386","trade_money":"626660000","diff_money":"1.99","diff_rate":"4.95","swing":"5.83","turnover":"49.14","market":"sz","code":"002376"},{"date":"2010-03-24","open_price":"36.20","close_price":"40.17","max_price":"40.17","min_price":"35.68","trade_num":"173509","trade_money":"659730000","diff_money":"3.65","diff_rate":"9.99","swing":"12.29","turnover":"57.08","market":"sz","code":"002376"},{"date":"2010-03-23","open_price":"35.00","close_price":"36.52","max_price":"36.79","min_price":"34.35","trade_num":"253684","trade_money":"902980000","diff_money":"13.94","diff_rate":"61.74","swing":"10.81","turnover":"83.45","market":"sz","code":"002376"}]}
                }
                
