{
                  "showapi_res_error": "",
                  "showapi_res_id": "d6c40886f2c44db6ab57e0649aa0aa65",
                  "showapi_res_code": 0,
                  "showapi_res_body": {"ret_code":0,"list":[{"date":"2016-12-19","open_price":"11.24","close_price":"11.42","max_price":"11.47","min_price":"11.2","trade_num":"231253","trade_money":"262689960","diff_money":"0.25","diff_rate":"2.24","swing":"2.42","turnover":"1.61","market":"sh","code":"600655"},{"date":"2016-12-16","open_price":"11.07","close_price":"11.17","max_price":"11.2","min_price":"11.01","trade_num":"100517","trade_money":"111832271","diff_money":"0.03","diff_rate":"0.27","swing":"1.71","turnover":"0.7","market":"sh","code":"600655"},{"date":"2016-12-15","open_price":"10.93","close_price":"11.14","max_price":"11.24","min_price":"10.89","trade_num":"114130","trade_money":"126197505","diff_money":"0.1","diff_rate":"0.91","swing":"3.17","turnover":"0.79","market":"sh","code":"600655"},{"date":"2016-12-14","open_price":"10.9","close_price":"11.04","max_price":"11.17","min_price":"10.86","trade_num":"102777","trade_money":"113324434","diff_money":"0.15","diff_rate":"1.38","swing":"2.85","turnover":"0.72","market":"sh","code":"600655"},{"date":"2016-12-13","open_price":"11.03","close_price":"10.89","max_price":"11.1","min_price":"10.79","trade_num":"123473","trade_money":"134965123","diff_money":"-0.22","diff_rate":"-1.98","swing":"2.79","turnover":"0.86","market":"sh","code":"600655"},{"date":"2016-12-12","open_price":"11.27","close_price":"11.11","max_price":"11.35","min_price":"10.95","trade_num":"208844","trade_money":"232960276","diff_money":"-0.16","diff_rate":"-1.42","swing":"3.55","turnover":"1.45","market":"sh","code":"600655"},{"date":"2016-12-09","open_price":"11.08","close_price":"11.27","max_price":"11.4","min_price":"11.03","trade_num":"228602","trade_money":"257625088","diff_money":"0.15","diff_rate":"1.35","swing":"3.33","turnover":"1.59","market":"sh","code":"600655"},{"date":"2016-12-08","open_price":"11.27","close_price":"11.12","max_price":"11.31","min_price":"11.1","trade_num":"114465","trade_money":"128106176","diff_money":"-0.13","diff_rate":"-1.16","swing":"1.87","turnover":"0.8","market":"sh","code":"600655"},{"date":"2016-12-07","open_price":"11.04","close_price":"11.25","max_price":"11.26","min_price":"11.01","trade_num":"141411","trade_money":"157877404","diff_money":"0.19","diff_rate":"1.72","swing":"2.26","turnover":"0.98","market":"sh","code":"600655"},{"date":"2016-12-06","open_price":"11.13","close_price":"11.06","max_price":"11.15","min_price":"11.05","trade_num":"62250","trade_money":"69125488","diff_money":"-0.06","diff_rate":"-0.54","swing":".90","turnover":"0.43","market":"sh","code":"600655"},{"date":"2016-12-05","open_price":"11.11","close_price":"11.12","max_price":"11.15","min_price":"11.04","trade_num":"75563","trade_money":"83860389","diff_money":"-0.03","diff_rate":"-0.27","swing":".99","turnover":"0.53","market":"sh","code":"600655"},{"date":"2016-12-02","open_price":"11.23","close_price":"11.15","max_price":"11.24","min_price":"11.14","trade_num":"91868","trade_money":"102736308","diff_money":"-0.09","diff_rate":"-0.8","swing":".89","turnover":"0.64","market":"sh","code":"600655"},{"date":"2016-12-01","open_price":"11.1","close_price":"11.24","max_price":"11.25","min_price":"11.08","trade_num":"96614","trade_money":"108211470","diff_money":"0.11","diff_rate":"0.99","swing":"1.53","turnover":"0.67","market":"sh","code":"600655"}]}
                }

